hubspot/__init__.py
hubspot/auth.py
hubspot/exceptions.py
hubspot/leads.py
hubspot/utils.py
salesforce/__init__.py
salesforce/auth.py
salesforce/exceptions.py
salesforce/leads.py
salesforce/utils.py
lead_crm_library-0.0.7.dist-info/METADATA
lead_crm_library-0.0.7.dist-info/WHEEL
lead_crm_library-0.0.7.dist-info/top_level.txt
lead_crm_library-0.0.7.dist-info/RECORD
