Metadata-Version: 2.1
Name: lead-crm-library
Version: 0.0.7
Summary: A library for managing generic leads in CRMs
Home-page: https://github.com/matiasnu/lead_crm_library
Author: Matias Nuñez
Author-email: matiasne45@gmail.com
License: MIT
Classifier: Development Status :: 3 - Alpha
Classifier: Intended Audience :: Developers
Classifier: Operating System :: OS Independent
Classifier: License :: OSI Approved :: MIT License
Classifier: Programming Language :: Python :: 3
Classifier: Programming Language :: Python :: 3.6
Classifier: Programming Language :: Python :: 3.7
Classifier: Programming Language :: Python :: 3.8
Classifier: Programming Language :: Python :: 3.9
Requires-Dist: simple-salesforce
Requires-Dist: hubspot
